inkscape_scripting/__init__.py
inkscape_scripting/client.py
inkscape_scripting/constants.py
inkscape_scripting/daemon.py
inkscape_scripting/interact.py
inkscape_scripting/interact_libxdo.py
inkscape_scripting/interact_xdotool.py
inkscape_scripting/ipython.py
inkscape_scripting/ipython_export.py
inkscape_scripting/object_repr.py
inkscape_scripting/py.typed
inkscape_scripting/shell.py
inkscape_scripting-0.1.0.dist-info/licenses/LICENSE
inkscape_scripting-0.1.0.dist-info/METADATA
inkscape_scripting-0.1.0.dist-info/WHEEL
inkscape_scripting-0.1.0.dist-info/entry_points.txt
inkscape_scripting-0.1.0.dist-info/top_level.txt
inkscape_scripting-0.1.0.dist-info/zip-safe
inkscape_scripting-0.1.0.dist-info/RECORD
