Metadata-Version: 2.4
Name: inkscape_scripting
Version: 0.1.0
Author: user202729
Project-URL: Source Code, https://github.com/user202729/inkscape-scripting
Project-URL: Issue Tracker, https://github.com/user202729/inkscape-scripting/issues
Classifier: Programming Language :: Python :: 3
Classifier: Programming Language :: Python :: 3.7
Classifier: Programming Language :: Python :: 3.8
Classifier: Programming Language :: Python :: 3.9
Classifier: Programming Language :: Python :: 3.10
Classifier: License :: OSI Approved :: GNU General Public License v3 or later (GPLv3+)
Classifier: Operating System :: POSIX :: Linux
Requires-Python: >=3.7
License-File: LICENSE
Requires-Dist: ipython>=8.18.1
Requires-Dist: python-libxdo>=0.1.2a1
Dynamic: license-file
